trojai/__init__.py
trojai/troj.py
trojai/attacks/ARTAttacks.py
trojai/attacks/NLP_attack_utils.py
trojai/attacks/TrojNLPAttacks.py
trojai/attacks/TrojNLPTransformations.py
trojai/attacks/VisionAttacksPytorch.py
trojai/attacks/__init__.py
trojai/client/Client.py
trojai/client/Session.py
trojai/client/__init__.py
trojai/client/client_utils.py
trojai/corruptions/Corruptions.py
trojai/corruptions/Transformations.py
trojai/corruptions/__init__.py
trojai/data/Loaders.py
trojai/data/MemoryBank.py
trojai/data/NLPData.py
trojai/data/__init__.py
trojai/data/data_utils.py
trojai/estimators/ClassifierBase.py
trojai/estimators/NLPClassifier.py
trojai/estimators/PytorchClassifier.py
trojai/estimators/PytorchObjectDetector.py
trojai/estimators/TensorflowClassifier.py
trojai/estimators/TensorflowV2Classifier.py
trojai/estimators/__init__.py
trojai/evaluators/ARTEvaluators.py
trojai/evaluators/LatentEvaluators.py
trojai/evaluators/NLPEvaluators.py
trojai/evaluators/NLP_utils.py
trojai/evaluators/VisionEvaluators.py
trojai/evaluators/__init__.py
trojai/logger/__init__.py
trojai/logger/logger.py
trojai/metrics/NLPMetrics.py
trojai/metrics/OutputParsers.py
trojai/metrics/__init__.py
trojai/metrics/mAP_utils.py
trojai/metrics/metric_utils.py
trojai/plots/__init__.py
trojai/plots/express.py
trojai/plots/ez_plots.py
trojai/tasks/__init__.py
trojai/tasks/tasks.py
troj-1.0.0.dist-info/LICENSE
troj-1.0.0.dist-info/METADATA
troj-1.0.0.dist-info/WHEEL
troj-1.0.0.dist-info/entry_points.txt
troj-1.0.0.dist-info/top_level.txt
troj-1.0.0.dist-info/RECORD
