Metadata-Version: 2.1
Name: troj
Version: 1.0.0
Summary: TrojAI provides the troj Python convenience package to allow users to integrate TrojAI adversarial protections and robustness metrics seamlessly into their AI development pipelines.
Home-page: https://troj.ai
Author: TrojAI
Author-email: stan.petley@troj.ai
License: UNKNOWN
Platform: UNKNOWN
Classifier: Programming Language :: Python :: 3
Classifier: Programming Language :: Python :: 3.6
Classifier: License :: OSI Approved :: MIT License
Classifier: Operating System :: OS Independent
Requires-Python: >=3.6
License-File: LICENSE
Requires-Dist: adversarial-robustness-toolbox (==1.8.1)
Requires-Dist: gensim (==4.1.2)
Requires-Dist: importlib-metadata (<4.0.0)
Requires-Dist: more-itertools (~=8.8.0)
Requires-Dist: numba
Requires-Dist: numpy (<1.21)
Requires-Dist: pandas (==1.3.4)
Requires-Dist: plotly (==5.4.0)
Requires-Dist: requests (==2.26.0)
Requires-Dist: scikit-learn (==1.0.1)
Requires-Dist: scipy (==1.7.3)
Requires-Dist: setuptools (==47.1.0)
Requires-Dist: tensorflow (==2.7.0)
Requires-Dist: tensorflow-gpu (==2.7.0)
Requires-Dist: torch (==1.10.0)
Requires-Dist: torchvision (==0.11.1)
Requires-Dist: tqdm (<4.50.0)
Requires-Dist: urllib3 (==1.26.7)
Provides-Extra: cv
Requires-Dist: torchvision (==0.11.1) ; extra == 'cv'
Requires-Dist: opencv-python (==4.5.4.60) ; extra == 'cv'
Requires-Dist: Pillow (==8.4.0) ; extra == 'cv'
Requires-Dist: scikit-image ; extra == 'cv'
Provides-Extra: dev
Requires-Dist: recommonmark ; extra == 'dev'
Requires-Dist: nbsphinx ; extra == 'dev'
Requires-Dist: sphinx-autobuild ; extra == 'dev'
Requires-Dist: sphinx-rtd-theme ; extra == 'dev'
Requires-Dist: docutils (<0.18) ; extra == 'dev'
Requires-Dist: pytest ; extra == 'dev'
Requires-Dist: tensorflow (==2.7.0) ; extra == 'dev'
Requires-Dist: tensorflow-gpu (==2.7.0) ; extra == 'dev'
Requires-Dist: textattack (==0.3.4) ; extra == 'dev'
Requires-Dist: spacy (==3.2.1) ; extra == 'dev'
Requires-Dist: nltk (==3.6.5) ; extra == 'dev'
Requires-Dist: transformers (==4.13.0) ; extra == 'dev'
Requires-Dist: tensorflow-text ; extra == 'dev'
Requires-Dist: torchvision (==0.11.1) ; extra == 'dev'
Requires-Dist: opencv-python (==4.5.4.60) ; extra == 'dev'
Requires-Dist: Pillow (==8.4.0) ; extra == 'dev'
Requires-Dist: scikit-image ; extra == 'dev'
Provides-Extra: docs
Requires-Dist: recommonmark ; extra == 'docs'
Requires-Dist: nbsphinx ; extra == 'docs'
Requires-Dist: sphinx-autobuild ; extra == 'docs'
Requires-Dist: sphinx-rtd-theme ; extra == 'docs'
Requires-Dist: docutils (<0.18) ; extra == 'docs'
Provides-Extra: nlp
Requires-Dist: textattack (==0.3.4) ; extra == 'nlp'
Requires-Dist: spacy (==3.2.1) ; extra == 'nlp'
Requires-Dist: nltk (==3.6.5) ; extra == 'nlp'
Requires-Dist: transformers (==4.13.0) ; extra == 'nlp'
Requires-Dist: tensorflow-text ; extra == 'nlp'
Provides-Extra: tensorflow
Requires-Dist: tensorflow (==2.7.0) ; extra == 'tensorflow'
Requires-Dist: tensorflow-gpu (==2.7.0) ; extra == 'tensorflow'
Provides-Extra: test
Requires-Dist: pytest ; extra == 'test'
